modelchoices/__init__.py
modelchoices/modelchoices.py
modelchoices/tests.py
django_model_choices-1.0.0.dist-info/LICENSE
django_model_choices-1.0.0.dist-info/METADATA
django_model_choices-1.0.0.dist-info/WHEEL
django_model_choices-1.0.0.dist-info/top_level.txt
django_model_choices-1.0.0.dist-info/RECORD
