Metadata-Version: 2.1
Name: django-model-choices
Version: 1.0.0
Summary: Django Model Choices provides a neat and DRY way to specify the `choices` option for a Django models and forms.
Home-page: https://gitlab.com/eeriksp/django-model-choices
Author: Eerik Sven Puudist
Author-email: eerik@herbfoods.eu
License: UNKNOWN
Platform: UNKNOWN
Classifier: Programming Language :: Python :: 3
Classifier: License :: OSI Approved :: MIT License
Classifier: Operating System :: OS Independent
Classifier: Framework :: Django
Classifier: Intended Audience :: Developers
